polydispers/__init__.py
polydispers/_version.py
polydispers/chain_generator.py
polydispers/cli.py
polydispers/core.py
polydispers/files_io.py
polydispers/input_config.py
polydispers/stats.py
polydispers/system_generator.py
polydispers/topology_config.py
polydispers/templates/__init__.py
polydispers/templates/lammps_in.j2
polydispers_lj_generator-0.3.3.dist-info/LICENSE
polydispers_lj_generator-0.3.3.dist-info/METADATA
polydispers_lj_generator-0.3.3.dist-info/WHEEL
polydispers_lj_generator-0.3.3.dist-info/entry_points.txt
polydispers_lj_generator-0.3.3.dist-info/top_level.txt
polydispers_lj_generator-0.3.3.dist-info/RECORD
