Metadata-Version: 2.1
Name: polydispers-lj-generator
Version: 0.3.3
Summary: A tool to generate polydisperse Lennard-Jones systems.
Author-email: Jakub Krajniak <jkrajniak@gmail.com>
License: MIT
Classifier: Programming Language :: Python :: 3
Classifier: License :: OSI Approved :: MIT License
Classifier: Operating System :: OS Independent
Classifier: Topic :: Scientific/Engineering :: Physics
Classifier: Topic :: Scientific/Engineering :: Chemistry
License-File: LICENSE
Requires-Dist: numpy
Requires-Dist: scipy
Requires-Dist: tqdm
Requires-Dist: pyyaml
Requires-Dist: click
Requires-Dist: jinja2
Provides-Extra: dev
Requires-Dist: pytest>=7.0; extra == "dev"
Requires-Dist: pytest-cov>=4.0; extra == "dev"
Provides-Extra: notebook
Requires-Dist: jupyter; extra == "notebook"
Requires-Dist: matplotlib; extra == "notebook"
Requires-Dist: seaborn; extra == "notebook"
Requires-Dist: pandas; extra == "notebook"
